lapkt/__init__.py
lapkt/load_planner.py
lapkt/parseargs.py
lapkt/cmake/lapkt-core-Targets-release.cmake
lapkt/cmake/lapkt-core-Targets.cmake
lapkt/cmake/lapkt-pddl-Targets-release.cmake
lapkt/cmake/lapkt-pddl-Targets.cmake
lapkt/cmake/lapkt-planner-Targets-release.cmake
lapkt/cmake/lapkt-planner-Targets.cmake
lapkt/cmake/lapkt-wrapper-Targets-release.cmake
lapkt/cmake/lapkt-wrapper-Targets.cmake
lapkt/cmake/lapktConfig.cmake
lapkt/cmake/lapktConfigVersion.cmake
lapkt/core/include/lapkt_cmake_config.h
lapkt/core/include/component/closed_list.hxx
lapkt/core/include/component/match_tree.hxx
lapkt/core/include/component/new_node_comparer.hxx
lapkt/core/include/component/open_list.hxx
lapkt/core/include/component/reachability.hxx
lapkt/core/include/component/watched_lit_succ_gen.hxx
lapkt/core/include/engine/approx_novelty_bfws_2h.hxx
lapkt/core/include/engine/approx_novelty_bfws_2h_M.hxx
lapkt/core/include/engine/approx_novelty_bfws_2h_consistency.hxx
lapkt/core/include/engine/approx_novelty_bfws_2h_consistency_M.hxx
lapkt/core/include/engine/approx_novelty_bfws_4h.hxx
lapkt/core/include/engine/approx_novelty_dfs_plus.hxx
lapkt/core/include/engine/approx_novelty_iw.hxx
lapkt/core/include/engine/approx_novelty_rp_iw.hxx
lapkt/core/include/engine/approx_novelty_serialized_search.hxx
lapkt/core/include/engine/approx_novelty_siw.hxx
lapkt/core/include/engine/approx_novelty_siw_plus.hxx
lapkt/core/include/engine/at_bfs.hxx
lapkt/core/include/engine/at_bfs_dq.hxx
lapkt/core/include/engine/at_bfs_dq_mh.hxx
lapkt/core/include/engine/at_gbfs.hxx
lapkt/core/include/engine/at_gbfs_3h.hxx
lapkt/core/include/engine/at_rwbfs_dq.hxx
lapkt/core/include/engine/at_rwbfs_dq_mh.hxx
lapkt/core/include/engine/at_wbfs.hxx
lapkt/core/include/engine/at_wbfs_dq.hxx
lapkt/core/include/engine/at_wbfs_dq_mh.hxx
lapkt/core/include/engine/bfws_2h.hxx
lapkt/core/include/engine/bfws_2h_M.hxx
lapkt/core/include/engine/bfws_2h_consistency.hxx
lapkt/core/include/engine/bfws_2h_consistency_M.hxx
lapkt-0.2.0.dist-info/METADATA
lapkt-0.2.0.dist-info/WHEEL
lapkt-0.2.0.dist-info/top_level.txt
lapkt-0.2.0.dist-info/RECORD
