Metadata-Version: 2.4
Name: lapkt
Version: 0.2.0
Summary: LAPKT planning toolkit
Home-page: https://github.com/LAPKT-dev/LAPKT-Public
Author: Anubhav Singh, Nir Lipovetzky, Miquel Ramirez, Christian Muise
Author-email: anubhav.singh.er@pm.me, nirlipo@gmail.com, miquel.ramirez@gmail.com, christian.muise@gmail.com
Classifier: Development Status :: 3 - Alpha
Classifier: Intended Audience :: Education
Classifier: Intended Audience :: Science/Research
Classifier: Intended Audience :: Developers
Classifier: Topic :: Scientific/Engineering :: Artificial Intelligence
Classifier: Programming Language :: Python :: 3
Classifier: License :: OSI Approved :: MIT License
Classifier: Operating System :: Microsoft :: Windows
Classifier: Operating System :: POSIX :: Linux
Requires-Python: >=3.7
Requires-Dist: tarski-lapkt[arithmetic,gringo]
Requires-Dist: ruamel.yaml
Dynamic: author
Dynamic: author-email
Dynamic: classifier
Dynamic: description-content-type
Dynamic: home-page
Dynamic: requires-dist
Dynamic: requires-python
Dynamic: summary
